Metadata-Version: 2.1
Name: factiva-country-code-mapping
Version: 1.0.1
Summary: A utility to simplify mapping Factiva country codes
Home-page: https://github.com/Supearnesh/factiva-country-code-mapping
Author: Supearnesh
Author-email: arnesh.sahay@gmail.com
License: UNKNOWN
Platform: UNKNOWN
Classifier: Programming Language :: Python :: 3
Classifier: License :: OSI Approved :: GNU Lesser General Public License v3 (LGPLv3)
Classifier: Operating System :: OS Independent
Requires-Python: >=3.6
